{"name":"Alicia Vikander","photo":null,"bio":null,"films":[{"id":"uDLFyHTjCZvQ","title":"The Wizard of the Kremlin","year":"2026","stars":null,"genres":[],"description":"Poetins spindoctor manipuleert macht en werkelijkheid in het Kremlin.","synopsis":"\"The Wizard of the Kremlin\" volgt de opkomst van Vadim Baranov, een voormalig televisieproducent die de invloedrijke spindoctor en strateeg van Vladimir Poetin wordt. Gebaseerd op de bestseller van Giuliano da Empoli, werpt de film een blik achter de schermen van de Russische macht en toont hoe Baranov de publieke opinie en de werkelijkheid manipuleert om de positie van de 'Tsaar' te consolideren. Het is een indringend politiek drama over de duistere mechanismen van het Kremlin en de transformatie van het moderne Rusland.","directors":["Oliver Hermanus"],"awards":[],"awardSummary":{"wins":0,"nominations":0}}],"awards":[],"awardSummary":{"wins":0,"nominations":0}}