{"name":"James Wan","photo":null,"bio":null,"films":[{"id":"ndA6UxWshruI","title":"Aquaman and the Lost Kingdom","year":"2023","stars":1,"genres":["Actie"],"description":"Aquaman redt de wereld met onwaarschijnlijke bondgenoot.","synopsis":"Nadat Black Manta de macht van de mythische Zwarte Drietand heeft ontketend om zijn vader te wreken, moet Arthur Curry een onwaarschijnlijke alliantie aangaan met zijn verbannen broer Orm. Terwijl hij zijn taken als koning van Atlantis en kersverse vader combineert, moet Aquaman samen met zijn voormalige vijand strijden om een eeuwenoud kwaad te stoppen en zijn koninkrijk, familie en de wereld te behoeden voor totale vernietiging.","awards":[],"awardSummary":{"wins":0,"nominations":0}},{"id":"5YanIYi_Fdmn","title":"Aquaman","year":"2018","stars":3,"genres":[],"description":null,"synopsis":null,"awards":[],"awardSummary":{"wins":0,"nominations":0}}],"awards":[],"awardSummary":{"wins":0,"nominations":0}}