{"name":"Reed Morano","photo":null,"bio":null,"films":[{"id":"JgA0lSm1IqDS","title":"The Good Boy","year":"2026","stars":null,"genres":[],"description":"Ontvoerde delinquent belandt in een duister heropvoedingsexperiment.","synopsis":"In de psychologische thriller *The Good Boy* (2026) wordt de negentienjarige delinquent Tommy ontvoerd door een ogenschijnlijk keurig echtpaar dat hem in hun kelder onderwerpt aan een extreme, bijna hondachtige heropvoeding. Terwijl zijn ontvoerders hem met manipulatieve methoden \"familiewaarden\" proberen bij te brengen, ontstaat er een duister machtsspel waarin de grens tussen rehabilitatie en psychologische marteling volledig vervaagt. De film toont een verontrustende strijd om controle binnen een verstikkende en dysfunctionele gezinsdynamiek.","awards":[],"awardSummary":{"wins":0,"nominations":0}}],"awards":[],"awardSummary":{"wins":0,"nominations":0}}